b3quant/__init__.py
b3quant/cli.py
b3quant/config.py
b3quant/downloaders/__init__.py
b3quant/downloaders/async_cotahist.py
b3quant/downloaders/cotahist.py
b3quant/models/__init__.py
b3quant/models/base.py
b3quant/models/black_scholes.py
b3quant/models/iv_solver.py
b3quant/parsers/__init__.py
b3quant/parsers/cotahist.py
b3quant/parsers/cotahist_metadata.py
b3quant/parsers/parallel_parser.py
b3quant/storage/__init__.py
b3quant/storage/parquet.py
b3quant/utils/__init__.py
b3quant/utils/cache.py
b3quant/utils/retry.py
b3quant/utils/validators.py
b3quant-0.1.16.dist-info/licenses/LICENSE
b3quant-0.1.16.dist-info/METADATA
b3quant-0.1.16.dist-info/WHEEL
b3quant-0.1.16.dist-info/entry_points.txt
b3quant-0.1.16.dist-info/top_level.txt
b3quant-0.1.16.dist-info/RECORD
