Metadata-Version: 2.4
Name: b3quant
Version: 0.1.16
Summary: Python library for downloading and parsing B3 (Brazilian Stock Exchange) market data
Author-email: Renan Alves <renanalvees@gmail.com>
License: MIT
Project-URL: Homepage, https://github.com/renves/b3quant
Project-URL: Documentation, https://b3quant.readthedocs.io
Project-URL: Repository, https://github.com/renves/b3quant
Project-URL: Issues, https://github.com/renves/b3quant/issues
Project-URL: Changelog, https://github.com/renves/b3quant/blob/main/CHANGELOG.md
Keywords: b3,bovespa,finance,stocks,options,brazil,market-data
Classifier: Development Status :: 3 - Alpha
Classifier: Intended Audience :: Financial and Insurance Industry
Classifier: Intended Audience :: Developers
Classifier: Topic :: Office/Business :: Financial :: Investment
Classifier: License :: OSI Approved :: MIT License
Classifier: Programming Language :: Python :: 3
Classifier: Programming Language :: Python :: 3.10
Classifier: Programming Language :: Python :: 3.11
Classifier: Programming Language :: Python :: 3.12
Classifier: Operating System :: OS Independent
Requires-Python: >=3.10
License-File: LICENSE
Requires-Dist: pandas>=2.0.0
Requires-Dist: requests>=2.31.0
Requires-Dist: scipy>=1.10.0
Requires-Dist: tqdm>=4.65.0
Requires-Dist: pyarrow>=14.0.0
Requires-Dist: httpx>=0.26.0
Requires-Dist: typer>=0.9.0
Provides-Extra: dev
Requires-Dist: pytest>=7.4.0; extra == "dev"
Requires-Dist: pytest-cov>=4.1.0; extra == "dev"
Requires-Dist: pytest-asyncio>=0.23.0; extra == "dev"
Requires-Dist: black>=23.0.0; extra == "dev"
Requires-Dist: mypy>=1.5.0; extra == "dev"
Requires-Dist: ruff>=0.1.0; extra == "dev"
Requires-Dist: ipython>=8.0.0; extra == "dev"
Requires-Dist: jupyter>=1.0.0; extra == "dev"
Requires-Dist: pandas-stubs>=2.0.0; extra == "dev"
Requires-Dist: types-requests>=2.31.0; extra == "dev"
Requires-Dist: types-tqdm>=4.65.0; extra == "dev"
Dynamic: license-file
